{
  "type": "File",
  "start": 0,
  "end": 1516,
  "loc": {
    "start": {
      "line": 1,
      "column": 0,
      "index": 0
    },
    "end": {
      "line": 47,
      "column": 21,
      "index": 1516
    }
  },
  "errors": [],
  "program": {
    "type": "Program",
    "start": 0,
    "end": 1516,
    "loc": {
      "start": {
        "line": 1,
        "column": 0,
        "index": 0
      },
      "end": {
        "line": 47,
        "column": 21,
        "index": 1516
      }
    },
    "sourceType": "module",
    "interpreter": null,
    "body": [
      {
        "type": "ImportDeclaration",
        "start": 0,
        "end": 45,
        "loc": {
          "start": {
            "line": 1,
            "column": 0,
            "index": 0
          },
          "end": {
            "line": 1,
            "column": 45,
            "index": 45
          }
        },
        "specifiers": [
          {
            "type": "ImportSpecifier",
            "start": 9,
            "end": 17,
            "loc": {
              "start": {
                "line": 1,
                "column": 9,
                "index": 9
              },
              "end": {
                "line": 1,
                "column": 17,
                "index": 17
              }
            },
            "imported": {
              "type": "Identifier",
              "start": 9,
              "end": 17,
              "loc": {
                "start": {
                  "line": 1,
                  "column": 9,
                  "index": 9
                },
                "end": {
                  "line": 1,
                  "column": 17,
                  "index": 17
                },
                "identifierName": "isString"
              },
              "name": "isString"
            },
            "local": {
              "type": "Identifier",
              "start": 9,
              "end": 17,
              "loc": {
                "start": {
                  "line": 1,
                  "column": 9,
                  "index": 9
                },
                "end": {
                  "line": 1,
                  "column": 17,
                  "index": 17
                },
                "identifierName": "isString"
              },
              "name": "isString"
            }
          }
        ],
        "source": {
          "type": "StringLiteral",
          "start": 25,
          "end": 44,
          "loc": {
            "start": {
              "line": 1,
              "column": 25,
              "index": 25
            },
            "end": {
              "line": 1,
              "column": 44,
              "index": 44
            }
          },
          "extra": {
            "rawValue": "@abw/badger-utils",
            "raw": "'@abw/badger-utils'"
          },
          "value": "@abw/badger-utils"
        }
      },
      {
        "type": "ImportDeclaration",
        "start": 46,
        "end": 75,
        "loc": {
          "start": {
            "line": 2,
            "column": 0,
            "index": 46
          },
          "end": {
            "line": 2,
            "column": 29,
            "index": 75
          }
        },
        "specifiers": [
          {
            "type": "ImportDefaultSpecifier",
            "start": 53,
            "end": 60,
            "loc": {
              "start": {
                "line": 2,
                "column": 7,
                "index": 53
              },
              "end": {
                "line": 2,
                "column": 14,
                "index": 60
              }
            },
            "local": {
              "type": "Identifier",
              "start": 53,
              "end": 60,
              "loc": {
                "start": {
                  "line": 2,
                  "column": 7,
                  "index": 53
                },
                "end": {
                  "line": 2,
                  "column": 14,
                  "index": 60
                },
                "identifierName": "prompts"
              },
              "name": "prompts"
            }
          }
        ],
        "source": {
          "type": "StringLiteral",
          "start": 66,
          "end": 75,
          "loc": {
            "start": {
              "line": 2,
              "column": 20,
              "index": 66
            },
            "end": {
              "line": 2,
              "column": 29,
              "index": 75
            }
          },
          "extra": {
            "rawValue": "prompts",
            "raw": "'prompts'"
          },
          "value": "prompts"
        },
        "trailingComments": [
          {
            "type": "CommentBlock",
            "value": "*\n * Prompt user to enter a value.\n * @param {String} question - question to prompt user to answer\n * @param {Object} [options] - optional options\n * @param {String} [options.default] - default value returned if user presses RETURN\n * @return {Promise} fulfills with response to question or default value\n * @example\n * prompt(\"What is your name?\")\n *   .then( name => console.log(`Hello ${name}`) );\n * @example\n * prompt(\"What is your name?\", { default: 'Mr.Badger' })\n *   .then( name => console.log(`Hello ${name}`) );\n ",
            "start": 77,
            "end": 605,
            "loc": {
              "start": {
                "line": 4,
                "column": 0,
                "index": 77
              },
              "end": {
                "line": 16,
                "column": 3,
                "index": 605
              }
            }
          }
        ]
      },
      {
        "type": "ExportNamedDeclaration",
        "start": 606,
        "end": 959,
        "loc": {
          "start": {
            "line": 17,
            "column": 0,
            "index": 606
          },
          "end": {
            "line": 32,
            "column": 1,
            "index": 959
          }
        },
        "specifiers": [],
        "source": null,
        "declaration": {
          "type": "VariableDeclaration",
          "start": 613,
          "end": 959,
          "loc": {
            "start": {
              "line": 17,
              "column": 7,
              "index": 613
            },
            "end": {
              "line": 32,
              "column": 1,
              "index": 959
            }
          },
          "declarations": [
            {
              "type": "VariableDeclarator",
              "start": 619,
              "end": 959,
              "loc": {
                "start": {
                  "line": 17,
                  "column": 13,
                  "index": 619
                },
                "end": {
                  "line": 32,
                  "column": 1,
                  "index": 959
                }
              },
              "id": {
                "type": "Identifier",
                "start": 619,
                "end": 625,
                "loc": {
                  "start": {
                    "line": 17,
                    "column": 13,
                    "index": 619
                  },
                  "end": {
                    "line": 17,
                    "column": 19,
                    "index": 625
                  },
                  "identifierName": "prompt"
                },
                "name": "prompt"
              },
              "init": {
                "type": "ArrowFunctionExpression",
                "start": 628,
                "end": 959,
                "loc": {
                  "start": {
                    "line": 17,
                    "column": 22,
                    "index": 628
                  },
                  "end": {
                    "line": 32,
                    "column": 1,
                    "index": 959
                  }
                },
                "id": {
                  "type": "Identifier",
                  "start": 619,
                  "end": 625,
                  "loc": {
                    "start": {
                      "line": 17,
                      "column": 13,
                      "index": 619
                    },
                    "end": {
                      "line": 17,
                      "column": 19,
                      "index": 625
                    },
                    "identifierName": "prompt"
                  },
                  "name": "prompt"
                },
                "generator": false,
                "async": true,
                "params": [
                  {
                    "type": "Identifier",
                    "start": 635,
                    "end": 643,
                    "loc": {
                      "start": {
                        "line": 17,
                        "column": 29,
                        "index": 635
                      },
                      "end": {
                        "line": 17,
                        "column": 37,
                        "index": 643
                      },
                      "identifierName": "question"
                    },
                    "name": "question"
                  },
                  {
                    "type": "AssignmentPattern",
                    "start": 645,
                    "end": 655,
                    "loc": {
                      "start": {
                        "line": 17,
                        "column": 39,
                        "index": 645
                      },
                      "end": {
                        "line": 17,
                        "column": 49,
                        "index": 655
                      }
                    },
                    "left": {
                      "type": "Identifier",
                      "start": 645,
                      "end": 652,
                      "loc": {
                        "start": {
                          "line": 17,
                          "column": 39,
                          "index": 645
                        },
                        "end": {
                          "line": 17,
                          "column": 46,
                          "index": 652
                        },
                        "identifierName": "options"
                      },
                      "name": "options"
                    },
                    "right": {
                      "type": "ObjectExpression",
                      "start": 653,
                      "end": 655,
                      "loc": {
                        "start": {
                          "line": 17,
                          "column": 47,
                          "index": 653
                        },
                        "end": {
                          "line": 17,
                          "column": 49,
                          "index": 655
                        }
                      },
                      "properties": []
                    }
                  }
                ],
                "body": {
                  "type": "BlockStatement",
                  "start": 660,
                  "end": 959,
                  "loc": {
                    "start": {
                      "line": 17,
                      "column": 54,
                      "index": 660
                    },
                    "end": {
                      "line": 32,
                      "column": 1,
                      "index": 959
                    }
                  },
                  "body": [
                    {
                      "type": "ExpressionStatement",
                      "start": 664,
                      "end": 733,
                      "loc": {
                        "start": {
                          "line": 18,
                          "column": 2,
                          "index": 664
                        },
                        "end": {
                          "line": 20,
                          "column": 14,
                          "index": 733
                        }
                      },
                      "expression": {
                        "type": "AssignmentExpression",
                        "start": 664,
                        "end": 732,
                        "loc": {
                          "start": {
                            "line": 18,
                            "column": 2,
                            "index": 664
                          },
                          "end": {
                            "line": 20,
                            "column": 13,
                            "index": 732
                          }
                        },
                        "operator": "=",
                        "left": {
                          "type": "Identifier",
                          "start": 664,
                          "end": 671,
                          "loc": {
                            "start": {
                              "line": 18,
                              "column": 2,
                              "index": 664
                            },
                            "end": {
                              "line": 18,
                              "column": 9,
                              "index": 671
                            },
                            "identifierName": "options"
                          },
                          "name": "options"
                        },
                        "right": {
                          "type": "ConditionalExpression",
                          "start": 674,
                          "end": 732,
                          "loc": {
                            "start": {
                              "line": 18,
                              "column": 12,
                              "index": 674
                            },
                            "end": {
                              "line": 20,
                              "column": 13,
                              "index": 732
                            }
                          },
                          "test": {
                            "type": "CallExpression",
                            "start": 674,
                            "end": 691,
                            "loc": {
                              "start": {
                                "line": 18,
                                "column": 12,
                                "index": 674
                              },
                              "end": {
                                "line": 18,
                                "column": 29,
                                "index": 691
                              }
                            },
                            "callee": {
                              "type": "Identifier",
                              "start": 674,
                              "end": 682,
                              "loc": {
                                "start": {
                                  "line": 18,
                                  "column": 12,
                                  "index": 674
                                },
                                "end": {
                                  "line": 18,
                                  "column": 20,
                                  "index": 682
                                },
                                "identifierName": "isString"
                              },
                              "name": "isString"
                            },
                            "arguments": [
                              {
                                "type": "Identifier",
                                "start": 683,
                                "end": 690,
                                "loc": {
                                  "start": {
                                    "line": 18,
                                    "column": 21,
                                    "index": 683
                                  },
                                  "end": {
                                    "line": 18,
                                    "column": 28,
                                    "index": 690
                                  },
                                  "identifierName": "options"
                                },
                                "name": "options"
                              }
                            ]
                          },
                          "consequent": {
                            "type": "ObjectExpression",
                            "start": 698,
                            "end": 718,
                            "loc": {
                              "start": {
                                "line": 19,
                                "column": 6,
                                "index": 698
                              },
                              "end": {
                                "line": 19,
                                "column": 26,
                                "index": 718
                              }
                            },
                            "properties": [
                              {
                                "type": "ObjectProperty",
                                "start": 700,
                                "end": 716,
                                "loc": {
                                  "start": {
                                    "line": 19,
                                    "column": 8,
                                    "index": 700
                                  },
                                  "end": {
                                    "line": 19,
                                    "column": 24,
                                    "index": 716
                                  }
                                },
                                "method": false,
                                "key": {
                                  "type": "Identifier",
                                  "start": 700,
                                  "end": 707,
                                  "loc": {
                                    "start": {
                                      "line": 19,
                                      "column": 8,
                                      "index": 700
                                    },
                                    "end": {
                                      "line": 19,
                                      "column": 15,
                                      "index": 707
                                    },
                                    "identifierName": "default"
                                  },
                                  "name": "default"
                                },
                                "computed": false,
                                "shorthand": false,
                                "value": {
                                  "type": "Identifier",
                                  "start": 709,
                                  "end": 716,
                                  "loc": {
                                    "start": {
                                      "line": 19,
                                      "column": 17,
                                      "index": 709
                                    },
                                    "end": {
                                      "line": 19,
                                      "column": 24,
                                      "index": 716
                                    },
                                    "identifierName": "options"
                                  },
                                  "name": "options"
                                }
                              }
                            ]
                          },
                          "alternate": {
                            "type": "Identifier",
                            "start": 725,
                            "end": 732,
                            "loc": {
                              "start": {
                                "line": 20,
                                "column": 6,
                                "index": 725
                              },
                              "end": {
                                "line": 20,
                                "column": 13,
                                "index": 732
                              },
                              "identifierName": "options"
                            },
                            "name": "options"
                          }
                        }
                      }
                    },
                    {
                      "type": "VariableDeclaration",
                      "start": 737,
                      "end": 775,
                      "loc": {
                        "start": {
                          "line": 22,
                          "column": 2,
                          "index": 737
                        },
                        "end": {
                          "line": 22,
                          "column": 40,
                          "index": 775
                        }
                      },
                      "declarations": [
                        {
                          "type": "VariableDeclarator",
                          "start": 743,
                          "end": 774,
                          "loc": {
                            "start": {
                              "line": 22,
                              "column": 8,
                              "index": 743
                            },
                            "end": {
                              "line": 22,
                              "column": 39,
                              "index": 774
                            }
                          },
                          "id": {
                            "type": "Identifier",
                            "start": 743,
                            "end": 747,
                            "loc": {
                              "start": {
                                "line": 22,
                                "column": 8,
                                "index": 743
                              },
                              "end": {
                                "line": 22,
                                "column": 12,
                                "index": 747
                              },
                              "identifierName": "name"
                            },
                            "name": "name"
                          },
                          "init": {
                            "type": "LogicalExpression",
                            "start": 750,
                            "end": 774,
                            "loc": {
                              "start": {
                                "line": 22,
                                "column": 15,
                                "index": 750
                              },
                              "end": {
                                "line": 22,
                                "column": 39,
                                "index": 774
                              }
                            },
                            "left": {
                              "type": "MemberExpression",
                              "start": 750,
                              "end": 762,
                              "loc": {
                                "start": {
                                  "line": 22,
                                  "column": 15,
                                  "index": 750
                                },
                                "end": {
                                  "line": 22,
                                  "column": 27,
                                  "index": 762
                                }
                              },
                              "object": {
                                "type": "Identifier",
                                "start": 750,
                                "end": 757,
                                "loc": {
                                  "start": {
                                    "line": 22,
                                    "column": 15,
                                    "index": 750
                                  },
                                  "end": {
                                    "line": 22,
                                    "column": 22,
                                    "index": 757
                                  },
                                  "identifierName": "options"
                                },
                                "name": "options"
                              },
                              "computed": false,
                              "property": {
                                "type": "Identifier",
                                "start": 758,
                                "end": 762,
                                "loc": {
                                  "start": {
                                    "line": 22,
                                    "column": 23,
                                    "index": 758
                                  },
                                  "end": {
                                    "line": 22,
                                    "column": 27,
                                    "index": 762
                                  },
                                  "identifierName": "name"
                                },
                                "name": "name"
                              }
                            },
                            "operator": "||",
                            "right": {
                              "type": "StringLiteral",
                              "start": 766,
                              "end": 774,
                              "loc": {
                                "start": {
                                  "line": 22,
                                  "column": 31,
                                  "index": 766
                                },
                                "end": {
                                  "line": 22,
                                  "column": 39,
                                  "index": 774
                                }
                              },
                              "extra": {
                                "rawValue": "answer",
                                "raw": "'answer'"
                              },
                              "value": "answer"
                            }
                          }
                        }
                      ],
                      "kind": "const"
                    },
                    {
                      "type": "VariableDeclaration",
                      "start": 778,
                      "end": 933,
                      "loc": {
                        "start": {
                          "line": 23,
                          "column": 2,
                          "index": 778
                        },
                        "end": {
                          "line": 30,
                          "column": 5,
                          "index": 933
                        }
                      },
                      "declarations": [
                        {
                          "type": "VariableDeclarator",
                          "start": 784,
                          "end": 932,
                          "loc": {
                            "start": {
                              "line": 23,
                              "column": 8,
                              "index": 784
                            },
                            "end": {
                              "line": 30,
                              "column": 4,
                              "index": 932
                            }
                          },
                          "id": {
                            "type": "Identifier",
                            "start": 784,
                            "end": 791,
                            "loc": {
                              "start": {
                                "line": 23,
                                "column": 8,
                                "index": 784
                              },
                              "end": {
                                "line": 23,
                                "column": 15,
                                "index": 791
                              },
                              "identifierName": "answers"
                            },
                            "name": "answers"
                          },
                          "init": {
                            "type": "AwaitExpression",
                            "start": 794,
                            "end": 932,
                            "loc": {
                              "start": {
                                "line": 23,
                                "column": 18,
                                "index": 794
                              },
                              "end": {
                                "line": 30,
                                "column": 4,
                                "index": 932
                              }
                            },
                            "argument": {
                              "type": "CallExpression",
                              "start": 800,
                              "end": 932,
                              "loc": {
                                "start": {
                                  "line": 23,
                                  "column": 24,
                                  "index": 800
                                },
                                "end": {
                                  "line": 30,
                                  "column": 4,
                                  "index": 932
                                }
                              },
                              "callee": {
                                "type": "Identifier",
                                "start": 800,
                                "end": 807,
                                "loc": {
                                  "start": {
                                    "line": 23,
                                    "column": 24,
                                    "index": 800
                                  },
                                  "end": {
                                    "line": 23,
                                    "column": 31,
                                    "index": 807
                                  },
                                  "identifierName": "prompts"
                                },
                                "name": "prompts"
                              },
                              "arguments": [
                                {
                                  "type": "ArrayExpression",
                                  "start": 808,
                                  "end": 931,
                                  "loc": {
                                    "start": {
                                      "line": 23,
                                      "column": 32,
                                      "index": 808
                                    },
                                    "end": {
                                      "line": 30,
                                      "column": 3,
                                      "index": 931
                                    }
                                  },
                                  "extra": {
                                    "trailingComma": 926
                                  },
                                  "elements": [
                                    {
                                      "type": "ObjectExpression",
                                      "start": 814,
                                      "end": 926,
                                      "loc": {
                                        "start": {
                                          "line": 24,
                                          "column": 4,
                                          "index": 814
                                        },
                                        "end": {
                                          "line": 29,
                                          "column": 5,
                                          "index": 926
                                        }
                                      },
                                      "properties": [
                                        {
                                          "type": "ObjectProperty",
                                          "start": 822,
                                          "end": 826,
                                          "loc": {
                                            "start": {
                                              "line": 25,
                                              "column": 6,
                                              "index": 822
                                            },
                                            "end": {
                                              "line": 25,
                                              "column": 10,
                                              "index": 826
                                            }
                                          },
                                          "method": false,
                                          "key": {
                                            "type": "Identifier",
                                            "start": 822,
                                            "end": 826,
                                            "loc": {
                                              "start": {
                                                "line": 25,
                                                "column": 6,
                                                "index": 822
                                              },
                                              "end": {
                                                "line": 25,
                                                "column": 10,
                                                "index": 826
                                              },
                                              "identifierName": "name"
                                            },
                                            "name": "name"
                                          },
                                          "computed": false,
                                          "shorthand": true,
                                          "value": {
                                            "type": "Identifier",
                                            "start": 822,
                                            "end": 826,
                                            "loc": {
                                              "start": {
                                                "line": 25,
                                                "column": 6,
                                                "index": 822
                                              },
                                              "end": {
                                                "line": 25,
                                                "column": 10,
                                                "index": 826
                                              },
                                              "identifierName": "name"
                                            },
                                            "name": "name"
                                          },
                                          "extra": {
                                            "shorthand": true
                                          }
                                        },
                                        {
                                          "type": "ObjectProperty",
                                          "start": 834,
                                          "end": 862,
                                          "loc": {
                                            "start": {
                                              "line": 26,
                                              "column": 6,
                                              "index": 834
                                            },
                                            "end": {
                                              "line": 26,
                                              "column": 34,
                                              "index": 862
                                            }
                                          },
                                          "method": false,
                                          "key": {
                                            "type": "Identifier",
                                            "start": 834,
                                            "end": 838,
                                            "loc": {
                                              "start": {
                                                "line": 26,
                                                "column": 6,
                                                "index": 834
                                              },
                                              "end": {
                                                "line": 26,
                                                "column": 10,
                                                "index": 838
                                              },
                                              "identifierName": "type"
                                            },
                                            "name": "type"
                                          },
                                          "computed": false,
                                          "shorthand": false,
                                          "value": {
                                            "type": "LogicalExpression",
                                            "start": 840,
                                            "end": 862,
                                            "loc": {
                                              "start": {
                                                "line": 26,
                                                "column": 12,
                                                "index": 840
                                              },
                                              "end": {
                                                "line": 26,
                                                "column": 34,
                                                "index": 862
                                              }
                                            },
                                            "left": {
                                              "type": "MemberExpression",
                                              "start": 840,
                                              "end": 852,
                                              "loc": {
                                                "start": {
                                                  "line": 26,
                                                  "column": 12,
                                                  "index": 840
                                                },
                                                "end": {
                                                  "line": 26,
                                                  "column": 24,
                                                  "index": 852
                                                }
                                              },
                                              "object": {
                                                "type": "Identifier",
                                                "start": 840,
                                                "end": 847,
                                                "loc": {
                                                  "start": {
                                                    "line": 26,
                                                    "column": 12,
                                                    "index": 840
                                                  },
                                                  "end": {
                                                    "line": 26,
                                                    "column": 19,
                                                    "index": 847
                                                  },
                                                  "identifierName": "options"
                                                },
                                                "name": "options"
                                              },
                                              "computed": false,
                                              "property": {
                                                "type": "Identifier",
                                                "start": 848,
                                                "end": 852,
                                                "loc": {
                                                  "start": {
                                                    "line": 26,
                                                    "column": 20,
                                                    "index": 848
                                                  },
                                                  "end": {
                                                    "line": 26,
                                                    "column": 24,
                                                    "index": 852
                                                  },
                                                  "identifierName": "type"
                                                },
                                                "name": "type"
                                              }
                                            },
                                            "operator": "||",
                                            "right": {
                                              "type": "StringLiteral",
                                              "start": 856,
                                              "end": 862,
                                              "loc": {
                                                "start": {
                                                  "line": 26,
                                                  "column": 28,
                                                  "index": 856
                                                },
                                                "end": {
                                                  "line": 26,
                                                  "column": 34,
                                                  "index": 862
                                                }
                                              },
                                              "extra": {
                                                "rawValue": "text",
                                                "raw": "'text'"
                                              },
                                              "value": "text"
                                            }
                                          }
                                        },
                                        {
                                          "type": "ObjectProperty",
                                          "start": 870,
                                          "end": 887,
                                          "loc": {
                                            "start": {
                                              "line": 27,
                                              "column": 6,
                                              "index": 870
                                            },
                                            "end": {
                                              "line": 27,
                                              "column": 23,
                                              "index": 887
                                            }
                                          },
                                          "method": false,
                                          "key": {
                                            "type": "Identifier",
                                            "start": 870,
                                            "end": 877,
                                            "loc": {
                                              "start": {
                                                "line": 27,
                                                "column": 6,
                                                "index": 870
                                              },
                                              "end": {
                                                "line": 27,
                                                "column": 13,
                                                "index": 877
                                              },
                                              "identifierName": "message"
                                            },
                                            "name": "message"
                                          },
                                          "computed": false,
                                          "shorthand": false,
                                          "value": {
                                            "type": "Identifier",
                                            "start": 879,
                                            "end": 887,
                                            "loc": {
                                              "start": {
                                                "line": 27,
                                                "column": 15,
                                                "index": 879
                                              },
                                              "end": {
                                                "line": 27,
                                                "column": 23,
                                                "index": 887
                                              },
                                              "identifierName": "question"
                                            },
                                            "name": "question"
                                          }
                                        },
                                        {
                                          "type": "ObjectProperty",
                                          "start": 895,
                                          "end": 919,
                                          "loc": {
                                            "start": {
                                              "line": 28,
                                              "column": 6,
                                              "index": 895
                                            },
                                            "end": {
                                              "line": 28,
                                              "column": 30,
                                              "index": 919
                                            }
                                          },
                                          "method": false,
                                          "key": {
                                            "type": "Identifier",
                                            "start": 895,
                                            "end": 902,
                                            "loc": {
                                              "start": {
                                                "line": 28,
                                                "column": 6,
                                                "index": 895
                                              },
                                              "end": {
                                                "line": 28,
                                                "column": 13,
                                                "index": 902
                                              },
                                              "identifierName": "initial"
                                            },
                                            "name": "initial"
                                          },
                                          "computed": false,
                                          "shorthand": false,
                                          "value": {
                                            "type": "MemberExpression",
                                            "start": 904,
                                            "end": 919,
                                            "loc": {
                                              "start": {
                                                "line": 28,
                                                "column": 15,
                                                "index": 904
                                              },
                                              "end": {
                                                "line": 28,
                                                "column": 30,
                                                "index": 919
                                              }
                                            },
                                            "object": {
                                              "type": "Identifier",
                                              "start": 904,
                                              "end": 911,
                                              "loc": {
                                                "start": {
                                                  "line": 28,
                                                  "column": 15,
                                                  "index": 904
                                                },
                                                "end": {
                                                  "line": 28,
                                                  "column": 22,
                                                  "index": 911
                                                },
                                                "identifierName": "options"
                                              },
                                              "name": "options"
                                            },
                                            "computed": false,
                                            "property": {
                                              "type": "Identifier",
                                              "start": 912,
                                              "end": 919,
                                              "loc": {
                                                "start": {
                                                  "line": 28,
                                                  "column": 23,
                                                  "index": 912
                                                },
                                                "end": {
                                                  "line": 28,
                                                  "column": 30,
                                                  "index": 919
                                                },
                                                "identifierName": "default"
                                              },
                                              "name": "default"
                                            }
                                          }
                                        }
                                      ],
                                      "extra": {
                                        "trailingComma": 919
                                      }
                                    }
                                  ]
                                }
                              ]
                            }
                          }
                        }
                      ],
                      "kind": "const"
                    },
                    {
                      "type": "ReturnStatement",
                      "start": 936,
                      "end": 957,
                      "loc": {
                        "start": {
                          "line": 31,
                          "column": 2,
                          "index": 936
                        },
                        "end": {
                          "line": 31,
                          "column": 23,
                          "index": 957
                        }
                      },
                      "argument": {
                        "type": "MemberExpression",
                        "start": 943,
                        "end": 956,
                        "loc": {
                          "start": {
                            "line": 31,
                            "column": 9,
                            "index": 943
                          },
                          "end": {
                            "line": 31,
                            "column": 22,
                            "index": 956
                          }
                        },
                        "object": {
                          "type": "Identifier",
                          "start": 943,
                          "end": 950,
                          "loc": {
                            "start": {
                              "line": 31,
                              "column": 9,
                              "index": 943
                            },
                            "end": {
                              "line": 31,
                              "column": 16,
                              "index": 950
                            },
                            "identifierName": "answers"
                          },
                          "name": "answers"
                        },
                        "computed": true,
                        "property": {
                          "type": "Identifier",
                          "start": 951,
                          "end": 955,
                          "loc": {
                            "start": {
                              "line": 31,
                              "column": 17,
                              "index": 951
                            },
                            "end": {
                              "line": 31,
                              "column": 21,
                              "index": 955
                            },
                            "identifierName": "name"
                          },
                          "name": "name"
                        }
                      }
                    }
                  ],
                  "directives": []
                }
              }
            }
          ],
          "kind": "const",
          "leadingComments": [
            {
              "type": "CommentBlock",
              "value": "*\n * Prompt user to enter a value.\n * @param {String} question - question to prompt user to answer\n * @param {Object} [options] - optional options\n * @param {String} [options.default] - default value returned if user presses RETURN\n * @return {Promise} fulfills with response to question or default value\n * @example\n * prompt(\"What is your name?\")\n *   .then( name => console.log(`Hello ${name}`) );\n * @example\n * prompt(\"What is your name?\", { default: 'Mr.Badger' })\n *   .then( name => console.log(`Hello ${name}`) );\n ",
              "start": 77,
              "end": 605,
              "loc": {
                "start": {
                  "line": 4,
                  "column": 0,
                  "index": 77
                },
                "end": {
                  "line": 16,
                  "column": 3,
                  "index": 605
                }
              }
            }
          ],
          "trailingComments": [
            {
              "type": "CommentBlock",
              "value": "*\n * Prompt user to confirm a choice.\n * @param {String} question - question to prompt user to answer\n * @param {Object} [options] - optional options\n * @param {String} [options.default] - default value returned if user presses RETURN\n * @return {Promise} fulfills with response to question or default value\n * @example\n * confirm(\"Are you sure?\")\n *   .then( yes => console.log('You said \"%s\"', yes ? 'YES' : 'NO') );\n ",
              "start": 961,
              "end": 1385,
              "loc": {
                "start": {
                  "line": 34,
                  "column": 0,
                  "index": 961
                },
                "end": {
                  "line": 43,
                  "column": 3,
                  "index": 1385
                }
              }
            }
          ]
        },
        "trailingComments": [
          {
            "type": "CommentBlock",
            "value": "*\n * Prompt user to confirm a choice.\n * @param {String} question - question to prompt user to answer\n * @param {Object} [options] - optional options\n * @param {String} [options.default] - default value returned if user presses RETURN\n * @return {Promise} fulfills with response to question or default value\n * @example\n * confirm(\"Are you sure?\")\n *   .then( yes => console.log('You said \"%s\"', yes ? 'YES' : 'NO') );\n ",
            "start": 961,
            "end": 1385,
            "loc": {
              "start": {
                "line": 34,
                "column": 0,
                "index": 961
              },
              "end": {
                "line": 43,
                "column": 3,
                "index": 1385
              }
            }
          }
        ],
        "leadingComments": [
          {
            "type": "CommentBlock",
            "value": "*\n * Prompt user to enter a value.\n * @param {String} question - question to prompt user to answer\n * @param {Object} [options] - optional options\n * @param {String} [options.default] - default value returned if user presses RETURN\n * @return {Promise} fulfills with response to question or default value\n * @example\n * prompt(\"What is your name?\")\n *   .then( name => console.log(`Hello ${name}`) );\n * @example\n * prompt(\"What is your name?\", { default: 'Mr.Badger' })\n *   .then( name => console.log(`Hello ${name}`) );\n ",
            "start": 77,
            "end": 605,
            "loc": {
              "start": {
                "line": 4,
                "column": 0,
                "index": 77
              },
              "end": {
                "line": 16,
                "column": 3,
                "index": 605
              }
            }
          }
        ]
      },
      {
        "type": "ExportNamedDeclaration",
        "start": 1386,
        "end": 1493,
        "loc": {
          "start": {
            "line": 44,
            "column": 0,
            "index": 1386
          },
          "end": {
            "line": 45,
            "column": 52,
            "index": 1493
          }
        },
        "specifiers": [],
        "source": null,
        "declaration": {
          "type": "VariableDeclaration",
          "start": 1393,
          "end": 1493,
          "loc": {
            "start": {
              "line": 44,
              "column": 7,
              "index": 1393
            },
            "end": {
              "line": 45,
              "column": 52,
              "index": 1493
            }
          },
          "declarations": [
            {
              "type": "VariableDeclarator",
              "start": 1399,
              "end": 1492,
              "loc": {
                "start": {
                  "line": 44,
                  "column": 13,
                  "index": 1399
                },
                "end": {
                  "line": 45,
                  "column": 51,
                  "index": 1492
                }
              },
              "id": {
                "type": "Identifier",
                "start": 1399,
                "end": 1406,
                "loc": {
                  "start": {
                    "line": 44,
                    "column": 13,
                    "index": 1399
                  },
                  "end": {
                    "line": 44,
                    "column": 20,
                    "index": 1406
                  },
                  "identifierName": "confirm"
                },
                "name": "confirm"
              },
              "init": {
                "type": "ArrowFunctionExpression",
                "start": 1409,
                "end": 1492,
                "loc": {
                  "start": {
                    "line": 44,
                    "column": 23,
                    "index": 1409
                  },
                  "end": {
                    "line": 45,
                    "column": 51,
                    "index": 1492
                  }
                },
                "id": {
                  "type": "Identifier",
                  "start": 1399,
                  "end": 1406,
                  "loc": {
                    "start": {
                      "line": 44,
                      "column": 13,
                      "index": 1399
                    },
                    "end": {
                      "line": 44,
                      "column": 20,
                      "index": 1406
                    },
                    "identifierName": "confirm"
                  },
                  "name": "confirm"
                },
                "generator": false,
                "async": true,
                "params": [
                  {
                    "type": "Identifier",
                    "start": 1416,
                    "end": 1424,
                    "loc": {
                      "start": {
                        "line": 44,
                        "column": 30,
                        "index": 1416
                      },
                      "end": {
                        "line": 44,
                        "column": 38,
                        "index": 1424
                      },
                      "identifierName": "question"
                    },
                    "name": "question"
                  },
                  {
                    "type": "AssignmentPattern",
                    "start": 1426,
                    "end": 1436,
                    "loc": {
                      "start": {
                        "line": 44,
                        "column": 40,
                        "index": 1426
                      },
                      "end": {
                        "line": 44,
                        "column": 50,
                        "index": 1436
                      }
                    },
                    "left": {
                      "type": "Identifier",
                      "start": 1426,
                      "end": 1433,
                      "loc": {
                        "start": {
                          "line": 44,
                          "column": 40,
                          "index": 1426
                        },
                        "end": {
                          "line": 44,
                          "column": 47,
                          "index": 1433
                        },
                        "identifierName": "options"
                      },
                      "name": "options"
                    },
                    "right": {
                      "type": "ObjectExpression",
                      "start": 1434,
                      "end": 1436,
                      "loc": {
                        "start": {
                          "line": 44,
                          "column": 48,
                          "index": 1434
                        },
                        "end": {
                          "line": 44,
                          "column": 50,
                          "index": 1436
                        }
                      },
                      "properties": []
                    }
                  }
                ],
                "body": {
                  "type": "CallExpression",
                  "start": 1443,
                  "end": 1492,
                  "loc": {
                    "start": {
                      "line": 45,
                      "column": 2,
                      "index": 1443
                    },
                    "end": {
                      "line": 45,
                      "column": 51,
                      "index": 1492
                    }
                  },
                  "callee": {
                    "type": "Identifier",
                    "start": 1443,
                    "end": 1449,
                    "loc": {
                      "start": {
                        "line": 45,
                        "column": 2,
                        "index": 1443
                      },
                      "end": {
                        "line": 45,
                        "column": 8,
                        "index": 1449
                      },
                      "identifierName": "prompt"
                    },
                    "name": "prompt"
                  },
                  "arguments": [
                    {
                      "type": "Identifier",
                      "start": 1450,
                      "end": 1458,
                      "loc": {
                        "start": {
                          "line": 45,
                          "column": 9,
                          "index": 1450
                        },
                        "end": {
                          "line": 45,
                          "column": 17,
                          "index": 1458
                        },
                        "identifierName": "question"
                      },
                      "name": "question"
                    },
                    {
                      "type": "ObjectExpression",
                      "start": 1460,
                      "end": 1491,
                      "loc": {
                        "start": {
                          "line": 45,
                          "column": 19,
                          "index": 1460
                        },
                        "end": {
                          "line": 45,
                          "column": 50,
                          "index": 1491
                        }
                      },
                      "properties": [
                        {
                          "type": "SpreadElement",
                          "start": 1462,
                          "end": 1472,
                          "loc": {
                            "start": {
                              "line": 45,
                              "column": 21,
                              "index": 1462
                            },
                            "end": {
                              "line": 45,
                              "column": 31,
                              "index": 1472
                            }
                          },
                          "argument": {
                            "type": "Identifier",
                            "start": 1465,
                            "end": 1472,
                            "loc": {
                              "start": {
                                "line": 45,
                                "column": 24,
                                "index": 1465
                              },
                              "end": {
                                "line": 45,
                                "column": 31,
                                "index": 1472
                              },
                              "identifierName": "options"
                            },
                            "name": "options"
                          }
                        },
                        {
                          "type": "ObjectProperty",
                          "start": 1474,
                          "end": 1489,
                          "loc": {
                            "start": {
                              "line": 45,
                              "column": 33,
                              "index": 1474
                            },
                            "end": {
                              "line": 45,
                              "column": 48,
                              "index": 1489
                            }
                          },
                          "method": false,
                          "key": {
                            "type": "Identifier",
                            "start": 1474,
                            "end": 1478,
                            "loc": {
                              "start": {
                                "line": 45,
                                "column": 33,
                                "index": 1474
                              },
                              "end": {
                                "line": 45,
                                "column": 37,
                                "index": 1478
                              },
                              "identifierName": "type"
                            },
                            "name": "type"
                          },
                          "computed": false,
                          "shorthand": false,
                          "value": {
                            "type": "StringLiteral",
                            "start": 1480,
                            "end": 1489,
                            "loc": {
                              "start": {
                                "line": 45,
                                "column": 39,
                                "index": 1480
                              },
                              "end": {
                                "line": 45,
                                "column": 48,
                                "index": 1489
                              }
                            },
                            "extra": {
                              "rawValue": "confirm",
                              "raw": "'confirm'"
                            },
                            "value": "confirm"
                          }
                        }
                      ]
                    }
                  ]
                }
              }
            }
          ],
          "kind": "const",
          "leadingComments": [
            {
              "type": "CommentBlock",
              "value": "*\n * Prompt user to confirm a choice.\n * @param {String} question - question to prompt user to answer\n * @param {Object} [options] - optional options\n * @param {String} [options.default] - default value returned if user presses RETURN\n * @return {Promise} fulfills with response to question or default value\n * @example\n * confirm(\"Are you sure?\")\n *   .then( yes => console.log('You said \"%s\"', yes ? 'YES' : 'NO') );\n ",
              "start": 961,
              "end": 1385,
              "loc": {
                "start": {
                  "line": 34,
                  "column": 0,
                  "index": 961
                },
                "end": {
                  "line": 43,
                  "column": 3,
                  "index": 1385
                }
              }
            }
          ],
          "trailingComments": []
        },
        "leadingComments": [
          {
            "type": "CommentBlock",
            "value": "*\n * Prompt user to confirm a choice.\n * @param {String} question - question to prompt user to answer\n * @param {Object} [options] - optional options\n * @param {String} [options.default] - default value returned if user presses RETURN\n * @return {Promise} fulfills with response to question or default value\n * @example\n * confirm(\"Are you sure?\")\n *   .then( yes => console.log('You said \"%s\"', yes ? 'YES' : 'NO') );\n ",
            "start": 961,
            "end": 1385,
            "loc": {
              "start": {
                "line": 34,
                "column": 0,
                "index": 961
              },
              "end": {
                "line": 43,
                "column": 3,
                "index": 1385
              }
            }
          }
        ]
      },
      {
        "type": "ExportDefaultDeclaration",
        "start": 1495,
        "end": 1516,
        "loc": {
          "start": {
            "line": 47,
            "column": 0,
            "index": 1495
          },
          "end": {
            "line": 47,
            "column": 21,
            "index": 1516
          }
        },
        "declaration": {
          "type": "Identifier",
          "start": 1510,
          "end": 1516,
          "loc": {
            "start": {
              "line": 47,
              "column": 15,
              "index": 1510
            },
            "end": {
              "line": 47,
              "column": 21,
              "index": 1516
            },
            "identifierName": "prompt"
          },
          "name": "prompt",
          "leadingComments": [],
          "trailingComments": []
        }
      }
    ],
    "directives": []
  },
  "comments": [
    {
      "type": "CommentBlock",
      "value": "*\n * Prompt user to enter a value.\n * @param {String} question - question to prompt user to answer\n * @param {Object} [options] - optional options\n * @param {String} [options.default] - default value returned if user presses RETURN\n * @return {Promise} fulfills with response to question or default value\n * @example\n * prompt(\"What is your name?\")\n *   .then( name => console.log(`Hello ${name}`) );\n * @example\n * prompt(\"What is your name?\", { default: 'Mr.Badger' })\n *   .then( name => console.log(`Hello ${name}`) );\n ",
      "start": 77,
      "end": 605,
      "loc": {
        "start": {
          "line": 4,
          "column": 0,
          "index": 77
        },
        "end": {
          "line": 16,
          "column": 3,
          "index": 605
        }
      }
    },
    {
      "type": "CommentBlock",
      "value": "*\n * Prompt user to confirm a choice.\n * @param {String} question - question to prompt user to answer\n * @param {Object} [options] - optional options\n * @param {String} [options.default] - default value returned if user presses RETURN\n * @return {Promise} fulfills with response to question or default value\n * @example\n * confirm(\"Are you sure?\")\n *   .then( yes => console.log('You said \"%s\"', yes ? 'YES' : 'NO') );\n ",
      "start": 961,
      "end": 1385,
      "loc": {
        "start": {
          "line": 34,
          "column": 0,
          "index": 961
        },
        "end": {
          "line": 43,
          "column": 3,
          "index": 1385
        }
      }
    }
  ]
}