{
  "coverage": "16.71%",
  "expectCount": 353,
  "actualCount": 59,
  "files": {
    "src/Badger/Component.js": {
      "expectCount": 5,
      "actualCount": 0,
      "undocumentLines": [
        3,
        4,
        5,
        6,
        10
      ]
    },
    "src/Badger/Config.js": {
      "expectCount": 8,
      "actualCount": 8,
      "undocumentLines": []
    },
    "src/Badger/Library.js": {
      "expectCount": 5,
      "actualCount": 5,
      "undocumentLines": []
    },
    "src/Badger/Utils/AppStatus.js": {
      "expectCount": 1,
      "actualCount": 0,
      "undocumentLines": [
        4
      ]
    },
    "src/Badger/Utils/CmdLine.js": {
      "expectCount": 4,
      "actualCount": 0,
      "undocumentLines": [
        5,
        7,
        72,
        82
      ]
    },
    "src/Badger/Utils/Color.js": {
      "expectCount": 34,
      "actualCount": 4,
      "undocumentLines": [
        3,
        4,
        5,
        92,
        93,
        94,
        95,
        96,
        97,
        98,
        99,
        100,
        101,
        102,
        103,
        104,
        105,
        106,
        107,
        108,
        109,
        110,
        111,
        112,
        113,
        114,
        115,
        116,
        117,
        118
      ]
    },
    "src/Badger/Utils/DataPath.js": {
      "expectCount": 5,
      "actualCount": 5,
      "undocumentLines": []
    },
    "src/Badger/Utils/Debug.js": {
      "expectCount": 2,
      "actualCount": 2,
      "undocumentLines": []
    },
    "src/Badger/Utils/Exit.js": {
      "expectCount": 3,
      "actualCount": 0,
      "undocumentLines": [
        3,
        10,
        14
      ]
    },
    "src/Badger/Utils/Misc.js": {
      "expectCount": 1,
      "actualCount": 1,
      "undocumentLines": []
    },
    "src/Badger/Utils/Options.js": {
      "expectCount": 5,
      "actualCount": 0,
      "undocumentLines": [
        7,
        18,
        232,
        240,
        257
      ]
    },
    "src/Badger/Utils/Params.js": {
      "expectCount": 4,
      "actualCount": 4,
      "undocumentLines": []
    },
    "src/Badger/Utils/Progress.js": {
      "expectCount": 31,
      "actualCount": 0,
      "undocumentLines": [
        7,
        13,
        20,
        63,
        70,
        94,
        104,
        118,
        125,
        126,
        145,
        146,
        147,
        148,
        149,
        150,
        151,
        152,
        153,
        154,
        155,
        156,
        157,
        158,
        159,
        163,
        183,
        195,
        218,
        222,
        227
      ]
    },
    "src/Badger/Utils/Prompt.js": {
      "expectCount": 3,
      "actualCount": 3,
      "undocumentLines": []
    },
    "src/Badger/Utils/Setup.js": {
      "expectCount": 7,
      "actualCount": 0,
      "undocumentLines": [
        11,
        38,
        44,
        167,
        177,
        189,
        246
      ]
    },
    "src/Badger/Utils/index.js": {
      "expectCount": 95,
      "actualCount": 0,
      "undocumentLines": [
        4,
        5,
        7,
        72,
        82,
        38,
        66,
        82,
        89,
        92,
        93,
        94,
        95,
        96,
        97,
        98,
        99,
        100,
        101,
        102,
        103,
        104,
        105,
        106,
        107,
        108,
        109,
        110,
        111,
        112,
        113,
        114,
        115,
        116,
        117,
        118,
        22,
        34,
        46,
        109,
        25,
        57,
        3,
        10,
        14,
        9,
        7,
        18,
        240,
        257,
        12,
        31,
        38,
        49,
        12,
        31,
        38,
        49,
        7,
        13,
        20,
        70,
        94,
        104,
        118,
        125,
        126,
        145,
        146,
        147,
        148,
        149,
        150,
        151,
        152,
        153,
        154,
        155,
        156,
        157,
        158,
        159,
        163,
        183,
        195,
        218,
        222,
        227,
        17,
        44,
        74,
        38,
        44,
        167,
        177
      ]
    },
    "src/Badger/Workspace.js": {
      "expectCount": 15,
      "actualCount": 11,
      "undocumentLines": [
        47,
        52,
        204,
        212
      ]
    },
    "src/Badger.js": {
      "expectCount": 125,
      "actualCount": 16,
      "undocumentLines": [
        3,
        4,
        5,
        6,
        10,
        20,
        123,
        18,
        70,
        4,
        5,
        7,
        72,
        82,
        38,
        66,
        82,
        89,
        92,
        93,
        94,
        95,
        96,
        97,
        98,
        99,
        100,
        101,
        102,
        103,
        104,
        105,
        106,
        107,
        108,
        109,
        110,
        111,
        112,
        113,
        114,
        115,
        116,
        117,
        118,
        22,
        34,
        46,
        109,
        25,
        57,
        3,
        10,
        14,
        9,
        7,
        18,
        240,
        257,
        12,
        31,
        38,
        49,
        12,
        31,
        38,
        49,
        7,
        13,
        20,
        70,
        94,
        104,
        118,
        125,
        126,
        145,
        146,
        147,
        148,
        149,
        150,
        151,
        152,
        153,
        154,
        155,
        156,
        157,
        158,
        159,
        163,
        183,
        195,
        218,
        222,
        227,
        17,
        44,
        74,
        38,
        44,
        167,
        177,
        27,
        47,
        52,
        204,
        212
      ]
    }
  }
}